{
    "key": "group_5ea8d51b8291f",
    "title": "Standup Settings",
    "fields": [
        {
            "key": "field_5ea8d521239c7",
            "label": "Title",
            "name": "standup_title",
            "type": "text",
            "instructions": "",
            "required": 0,
            "conditional_logic": 0,
            "wrapper": {
                "width": "",
                "class": "",
                "id": ""
            },
            "default_value": "",
            "placeholder": "",
            "prepend": "",
            "append": "",
            "maxlength": ""
        },
        {
            "key": "field_5ea8d527239c8",
            "label": "Content",
            "name": "standup_content",
            "type": "textarea",
            "instructions": "",
            "required": 0,
            "conditional_logic": 0,
            "wrapper": {
                "width": "",
                "class": "",
                "id": ""
            },
            "default_value": "",
            "placeholder": "",
            "maxlength": "",
            "rows": "",
            "new_lines": ""
        },
        {
            "key": "field_5ea9986a50863",
            "label": "Subtext",
            "name": "standup_subtext",
            "type": "text",
            "instructions": "",
            "required": 0,
            "conditional_logic": 0,
            "wrapper": {
                "width": "",
                "class": "",
                "id": ""
            },
            "default_value": "",
            "placeholder": "",
            "prepend": "",
            "append": "",
            "maxlength": ""
        },
        {
            "key": "field_5ea997b550862",
            "label": "Image",
            "name": "standup_image",
            "type": "image",
            "instructions": "",
            "required": 0,
            "conditional_logic": 0,
            "wrapper": {
                "width": "",
                "class": "",
                "id": ""
            },
            "return_format": "array",
            "preview_size": "medium",
            "library": "all",
            "min_width": "",
            "min_height": "",
            "min_size": "",
            "max_width": "",
            "max_height": "",
            "max_size": "",
            "mime_types": ""
        },
        {
            "key": "field_5eaa030ace051",
            "label": "Map",
            "name": "standup_map",
            "type": "text",
            "instructions": "",
            "required": 0,
            "conditional_logic": 0,
            "wrapper": {
                "width": "",
                "class": "",
                "id": ""
            },
            "default_value": "",
            "placeholder": "",
            "prepend": "",
            "append": "",
            "maxlength": ""
        },
        {
            "key": "field_5ea9a64873f4f",
            "label": "Form",
            "name": "standup_form",
            "type": "gravity_forms_field",
            "instructions": "",
            "required": 0,
            "conditional_logic": 0,
            "wrapper": {
                "width": "",
                "class": "",
                "id": ""
            },
            "allow_null": 0,
            "allow_multiple": 0
        },
        {
            "key": "field_5ea9ade68d485",
            "label": "Letter Pretext",
            "name": "letter_pretext",
            "type": "text",
            "instructions": "",
            "required": 0,
            "conditional_logic": 0,
            "wrapper": {
                "width": "",
                "class": "",
                "id": ""
            },
            "default_value": "",
            "placeholder": "",
            "prepend": "",
            "append": "",
            "maxlength": ""
        },
        {
            "key": "field_5ea8d6b9cb6b9",
            "label": "Default Letter",
            "name": "default_letter",
            "type": "wysiwyg",
            "instructions": "",
            "required": 0,
            "conditional_logic": 0,
            "wrapper": {
                "width": "",
                "class": "",
                "id": ""
            },
            "default_value": "",
            "tabs": "all",
            "toolbar": "full",
            "media_upload": 1,
            "delay": 0
        },
        {
            "key": "field_5ea8d5c6239c9",
            "label": "Letters",
            "name": "letters",
            "type": "repeater",
            "instructions": "",
            "required": 0,
            "conditional_logic": 0,
            "wrapper": {
                "width": "",
                "class": "",
                "id": ""
            },
            "collapsed": "field_5ea8d5e0239ca",
            "min": 0,
            "max": 0,
            "layout": "block",
            "button_label": "",
            "sub_fields": [
                {
                    "key": "field_5ea8d5e0239ca",
                    "label": "State",
                    "name": "state",
                    "type": "select",
                    "instructions": "",
                    "required": 0,
                    "conditional_logic": 0,
                    "wrapper": {
                        "width": "",
                        "class": "",
                        "id": ""
                    },
                    "choices": {
                        "AL": "Alabama",
                        "AK": "Alaska",
                        "AZ": "Arizona",
                        "AR": "Arkansas",
                        "CA": "California",
                        "CO": "Colorado",
                        "CT": "Connecticut",
                        "DE": "Delaware",
                        "FL": "Florida",
                        "GA": "Georgia",
                        "HI": "Hawaii",
                        "ID": "Idaho",
                        "IL": "Illinois",
                        "IN": "Indiana",
                        "IA": "Iowa",
                        "KS": "Kansas",
                        "KY": "Kentucky",
                        "LA": "Louisiana",
                        "ME": "Maine",
                        "MD": "Maryland",
                        "MA": "Massachusetts",
                        "MI": "Michigan",
                        "MN": "Minnesota",
                        "MS": "Mississippi",
                        "MO": "Missouri",
                        "MT": "Montana",
                        "NE": "Nebraska",
                        "NV": "Nevada",
                        "NH": "New Hampshire",
                        "NJ": "New Jersey",
                        "NM": "New Mexico",
                        "NY": "New York",
                        "NC": "North Carolina",
                        "ND": "North Dakota",
                        "OH": "Ohio",
                        "OK": "Oklahoma",
                        "OR": "Oregon",
                        "PA": "Pennsylvania",
                        "RI": "Rhode Island",
                        "SC": "South Carolina",
                        "SD": "South Dakota",
                        "TN": "Tennessee",
                        "TX": "Texas",
                        "UT": "Utah",
                        "VT": "Vermont",
                        "VA": "Virginia",
                        "WA": "Washington",
                        "WV": "West Virginia",
                        "WI": "Wisconsin",
                        "WY": "Wyoming"
                    },
                    "default_value": [],
                    "allow_null": 0,
                    "multiple": 0,
                    "ui": 0,
                    "return_format": "value",
                    "ajax": 0,
                    "placeholder": ""
                },
                {
                    "key": "field_5ea8d5eb239cb",
                    "label": "Content",
                    "name": "content",
                    "type": "wysiwyg",
                    "instructions": "",
                    "required": 0,
                    "conditional_logic": 0,
                    "wrapper": {
                        "width": "",
                        "class": "",
                        "id": ""
                    },
                    "default_value": "",
                    "tabs": "all",
                    "toolbar": "full",
                    "media_upload": 1,
                    "delay": 0
                }
            ]
        }
    ],
    "location": [
        [
            {
                "param": "options_page",
                "operator": "==",
                "value": "Standup-settings"
            }
        ]
    ],
    "menu_order": 0,
    "position": "normal",
    "style": "default",
    "label_placement": "top",
    "instruction_placement": "label",
    "hide_on_screen": "",
    "active": 1,
    "description": "",
    "metabox_title": "",
    "custom_css": "",
    "modified": 1588200220
}